cognitoinator/__init__.py
cognitoinator/providers.py
cognitoinator/scripts/cognito-profile-credential-fetcher
cognitoinator-0.2.2.data/scripts/cognito-profile-credential-fetcher
cognitoinator-0.2.2.dist-info/LICENSE
cognitoinator-0.2.2.dist-info/METADATA
cognitoinator-0.2.2.dist-info/WHEEL
cognitoinator-0.2.2.dist-info/top_level.txt
cognitoinator-0.2.2.dist-info/RECORD
