Metadata-Version: 2.1
Name: cognitoinator
Version: 0.2.2
Summary: Log into Cognito, assume an IAM role, directly access JWT's from your Cognito session, and use boto3 all with Cognito credentials
Home-page: https://github.com/QuiNovas/cognitoinator
Author: Mathew Moon
Author-email: mmoon@quinovas.com
License: Apache 2.0
Platform: UNKNOWN
Classifier: Development Status :: 4 - Beta
Classifier: Intended Audience :: Developers
Classifier: License :: OSI Approved :: Apache Software License
Classifier: Programming Language :: Python :: 3.8
Requires-Python: >=3.8
License-File: LICENSE
Requires-Dist: boto3
Requires-Dist: botocore
Requires-Dist: warrant
